{
  "$schema": "https://unpkg.com/knip@5/schema.json",
  "workspaces": {
    ".": {
      "entry": [
        "*.config.{js,ts,mjs}",
        "turbo.json"
      ],
      "ignore": [
        "**/*.d.ts",
        "**/dist/**",
        "**/out/**",
        "**/.turbo/**",
        "**/coverage/**",
        "**/build/**",
        "**/.next/**",
        "**/node_modules/**",
        "**/*.min.js"
      ],
      "ignoreBinaries": [
        "electron-builder"
      ]
    },
    "apps/electron": {
      "entry": [
        "src/main.ts",
        "src/renderer.tsx",
        "src/preload.ts",
        "electron.vite.config.ts"
      ],
      "project": [
        "src/**/*.{ts,tsx,js,jsx}"
      ],
      "ignore": [
        "**/*.d.ts",
        "**/dist/**",
        "**/out/**",
        "**/.turbo/**",
        "**/coverage/**",
        "**/build/**",
        "**/node_modules/**",
        "**/*.min.js"
      ],
      "ignoreBinaries": [
        "electron-rebuild"
      ]
    },
    "packages/shared": {
      "entry": [
      ],
      "project": [
        "src/**/*.ts"
      ],
      "ignore": [
        "**/*.d.ts",
        "**/dist/**",
        "**/.turbo/**",
        "**/node_modules/**",
        "**/*.test.ts",
        "**/*.spec.ts"
      ]
    },
    "packages/ui": {
      "entry": [
      ],
      "project": [
        "src/**/*.{ts,tsx}"
      ],
      "ignore": [
        "**/*.d.ts",
        "**/dist/**",
        "**/.turbo/**",
        "**/node_modules/**",
        "**/*.test.{ts,tsx}",
        "**/*.spec.{ts,tsx}",
        "**/*.stories.{ts,tsx}"
      ],
      "ignoreDependencies": []
    },
    "packages/tailwind-config": {
      "entry": [
      ],
      "project": [
        "*.js"
      ],
      "ignore": [
        "**/node_modules/**",
        "**/.turbo/**",
        "**/*.test.js",
        "**/*.spec.js"
      ],
      "ignoreDependencies": []
    }
  },
  "ignore": [
    "**/*.d.ts",
    "**/dist/**",
    "**/out/**",
    "**/.turbo/**",
    "**/.webpack/**",
    "**/coverage/**",
    "**/build/**",
    "**/.next/**",
    "**/node_modules/**",
    "**/*.min.js",
    "**/*.test.{ts,tsx,js,jsx}",
    "**/*.spec.{ts,tsx,js,jsx}",
    "**/forge.config.ts",
    "**/*.map",
    "**/*.log",
    "**/tmp/**",
    "**/temp/**"
  ],
  "ignoreDependencies": [],
  "ignoreWorkspaces": [],
  "rules": {
    "dependencies": "error",
    "devDependencies": "error",
    "optionalPeerDependencies": "off",
    "unlisted": "error",
    "binaries": "error",
    "unresolved": "error",
    "exports": "error",
    "nsExports": "error",
    "classMembers": "error",
    "types": "error",
    "nsTypes": "error",
    "enumMembers": "error",
    "duplicates": "error"
  }
}
